avdal/__init__.py
avdal/aes.py
avdal/annotations.py
avdal/dict.py
avdal/fs.py
avdal/logging.py
avdal/rbac.py
avdal/rsa.py
avdal/shell.py
avdal/aql/__init__.py
avdal/auth/__init__.py
avdal/auth/keycloak.py
avdal/cache/__init__.py
avdal/cache/memory.py
avdal/cache/redis.py
avdal/clients/__init__.py
avdal/clients/configs.py
avdal/clients/globals.py
avdal/clients/iam.py
avdal/clients/sendgrid.py
avdal/config/__init__.py
avdal/env/__init__.py
avdal/http/__init__.py
avdal/http/error.py
avdal/tokens/__init__.py
avdal/tokens/store/__init__.py
avdal/tokens/store/dynamodb.py
avdal/tokens/store/memory.py
avdal/tokens/store/sqlite.py
tests/__init__.py
tests/test_avdal.py
avdal-0.0.75.dist-info/LICENSE
avdal-0.0.75.dist-info/METADATA
avdal-0.0.75.dist-info/WHEEL
avdal-0.0.75.dist-info/top_level.txt
avdal-0.0.75.dist-info/RECORD
