Metadata-Version: 2.1
Name: avdal
Version: 0.0.75
Summary: Boilerplate python code used in my personal projects
Home-page: https://github.com/hazimavdal/pip
Author: Hazim Avdal
Author-email: apish.crab389@elevenpilots.com
Project-URL: Bug Tracker, https://github.com/hazimavdal/pip/issues
Classifier: Programming Language :: Python :: 3
Classifier: License :: OSI Approved :: MIT License
Classifier: Operating System :: OS Independent
Requires-Python: >=3.6
License-File: LICENSE
